ffAlive/__init__.py
ffAlive-1.0.7.dist-info/LICENSE
ffAlive-1.0.7.dist-info/METADATA
ffAlive-1.0.7.dist-info/WHEEL
ffAlive-1.0.7.dist-info/top_level.txt
ffAlive-1.0.7.dist-info/RECORD
