Metadata-Version: 2.1
Name: ffAlive
Version: 1.0.7
Summary: FFMPEG with Progress Bars
Home-page: https://github.com/thegreentimtam/ffAlive
Author: Tim Green
Author-email: the.green.timtam@gmail.com
License: MIT
License-File: LICENSE
Requires-Dist: alive-progress
Requires-Dist: ffmpeg-progress-yield
